redbayes_higueros/__init__.py
redbayes_higueros/network.py
redbayes_higueros/node.py
redbayes_higueros-1.0.0.dist-info/METADATA
redbayes_higueros-1.0.0.dist-info/WHEEL
redbayes_higueros-1.0.0.dist-info/top_level.txt
redbayes_higueros-1.0.0.dist-info/RECORD
