Metadata-Version: 2.1
Name: redbayes-higueros
Version: 1.0.0
Summary: Implementación de Red de Bayes sin utilizar librerias externas
Home-page: https://github.com/angelhigueros11/ia-lab2
Author: Angel Higueros
Author-email: hig20460@uvg.edu.gt
License: MIT
Requires-Dist: numpy
Requires-Dist: matplotlib
Requires-Dist: networkx
